CHANGELOG.txt
LICENSE.txt
MANIFEST.in
README.txt
ez_setup.py
setup.cfg
setup.py
BareNecessities.egg-info/PKG-INFO
BareNecessities.egg-info/SOURCES.txt
BareNecessities.egg-info/dependency_links.txt
BareNecessities.egg-info/entry_points.txt
BareNecessities.egg-info/not-zip-safe
BareNecessities.egg-info/requires.txt
BareNecessities.egg-info/top_level.txt
bn/__init__.py
bn/relimport_test.py
doc/Makefile
doc/index.txt
doc/source/conf.py
doc/source/index.rst
doc/source/manual.rst
test/README.txt
test/doc.py
test/html_escape_benchmark.py