Metadata-Version: 1.0
Name: BareNecessities
Version: 0.2.7
Summary: Provides the ``bn`` module containing a dictionary allowing attribute access to values - I use it so much I've made into a package.
Home-page: http://jimmyg.org/work/code/barenecessities/index.html
Author: James Gardner
Author-email: UNKNOWN
License: MIT
Platform: UNKNOWN
Classifier: Development Status :: 3 - Alpha
Classifier: License :: OSI Approved :: MIT License
Classifier: Programming Language :: Python :: 2
Classifier: Topic :: Software Development :: Libraries :: Python Modules
